loripsum/__init__.py
loripsum/__main__.py
loripsum/__version__.py
loripsum/client.py
loripsum-0.0.3.dist-info/entry_points.txt
loripsum-0.0.3.dist-info/WHEEL
loripsum-0.0.3.dist-info/METADATA
loripsum-0.0.3.dist-info/RECORD
